smokeshow/__init__.py
smokeshow/__main__.py
smokeshow/main.py
smokeshow/py.typed
smokeshow/version.py
smokeshow-0.5.0.dist-info/METADATA
smokeshow-0.5.0.dist-info/WHEEL
smokeshow-0.5.0.dist-info/entry_points.txt
smokeshow-0.5.0.dist-info/licenses/LICENSE
smokeshow-0.5.0.dist-info/RECORD
