Metadata-Version: 2.4
Name: smokeshow
Version: 0.5.0
Summary: Deploy ephemeral websites.
Project-URL: Homepage, https://smokeshow.helpmanual.io
Project-URL: Documentation, https://smokeshow.helpmanual.io
Project-URL: Funding, https://github.com/sponsors/samuelcolvin
Project-URL: Source, https://github.com/samuelcolvin/smokeshow
Project-URL: Changelog, https://github.com/samuelcolvin/smokeshow/releases
Author-email: Samuel Colvin <s@muelcolvin.com>
License-Expression: MIT
License-File: LICENSE
Classifier: Development Status :: 5 - Production/Stable
Classifier: Environment :: Console
Classifier: Environment :: MacOS X
Classifier: Environment :: Web Environment
Classifier: Intended Audience :: Developers
Classifier: Intended Audience :: Information Technology
Classifier: Intended Audience :: System Administrators
Classifier: License :: OSI Approved :: MIT License
Classifier: Operating System :: POSIX :: Linux
Classifier: Operating System :: Unix
Classifier: Programming Language :: Python
Classifier: Programming Language :: Python :: 3
Classifier: Programming Language :: Python :: 3 :: Only
Classifier: Programming Language :: Python :: 3.8
Classifier: Programming Language :: Python :: 3.9
Classifier: Programming Language :: Python :: 3.10
Classifier: Programming Language :: Python :: 3.11
Classifier: Topic :: Internet
Classifier: Topic :: Internet :: WWW/HTTP
Classifier: Topic :: Internet :: WWW/HTTP :: Site Management
Classifier: Topic :: Software Development :: Libraries :: Python Modules
Requires-Python: >=3.8
Requires-Dist: httpx>=0.24
Requires-Dist: typer>=0.8.0
